<annotation>
	<folder>hello</folder>
	<filename>hello.fcbf94df-8fc0-11ef-abd9-842afd3c393f.jpg</filename>
	<path>D:\Yams\RealTimeObjectDetection\Tensorflow\workspace\images\collection\hello\hello.fcbf94df-8fc0-11ef-abd9-842afd3c393f.jpg</path>
	<source>
		<database>Unknown</database>
	</source>
	<size>
		<width>640</width>
		<height>480</height>
		<depth>3</depth>
	</size>
	<segmented>0</segmented>
	<object>
		<name>hello</name>
		<pose>Unspecified</pose>
		<truncated>0</truncated>
		<difficult>0</difficult>
		<bndbox>
			<xmin>327</xmin>
			<ymin>2</ymin>
			<xmax>551</xmax>
			<ymax>272</ymax>
		</bndbox>
	</object>
</annotation>
