<annotation>
	<folder>Collectedimg</folder>
	<filename>thanks.f4702dc1-8fb7-11ef-8900-088fc3d3b735.jpg</filename>
	<path>C:\Users\Rishi Narayana\RealTimeObjectDetection\Tensorflow\workspace\images\Collectedimg\thanks.f4702dc1-8fb7-11ef-8900-088fc3d3b735.jpg</path>
	<source>
		<database>Unknown</database>
	</source>
	<size>
		<width>640</width>
		<height>480</height>
		<depth>3</depth>
	</size>
	<segmented>0</segmented>
	<object>
		<name>thanks</name>
		<pose>Unspecified</pose>
		<truncated>0</truncated>
		<difficult>0</difficult>
		<bndbox>
			<xmin>92</xmin>
			<ymin>323</ymin>
			<xmax>547</xmax>
			<ymax>469</ymax>
		</bndbox>
	</object>
</annotation>
